promptv/__init__.py
promptv/api_tester.py
promptv/cli.py
promptv/config_manager.py
promptv/cost_estimator.py
promptv/diff_engine.py
promptv/exceptions.py
promptv/interactive_tester.py
promptv/llm_providers.py
promptv/manager.py
promptv/models.py
promptv/secrets_manager.py
promptv/tag_manager.py
promptv/utils.py
promptv/variable_engine.py
promptv/resources/__init__.py
promptv/resources/pricing.yaml
promptv/sdk/__init__.py
promptv/sdk/client.py
promptv-0.1.7.post1.dist-info/licenses/LICENSE
promptv-0.1.7.post1.dist-info/METADATA
promptv-0.1.7.post1.dist-info/WHEEL
promptv-0.1.7.post1.dist-info/entry_points.txt
promptv-0.1.7.post1.dist-info/top_level.txt
promptv-0.1.7.post1.dist-info/RECORD
