Metadata-Version: 2.4
Name: promptv
Version: 0.1.7.post1
Summary: A comprehensive developer-first prompt management tool with git-like version control
Author: Thompson Wong
Author-email: Thompson Wong <thompsonwong@labs21.dev>
License:                                  Apache License
Project-URL: Homepage, https://github.com/thompson0012/promptv
Project-URL: Repository, https://github.com/thompson0012/promptv
Keywords: prompt,management,tool,git-like,version,control,developer-first
Requires-Python: >=3.11
License-File: LICENSE
Requires-Dist: click>=8.3.1
Requires-Dist: pydantic>=2.12.5
Requires-Dist: jinja2>=3.1.4
Requires-Dist: pyyaml>=6.0.2
Requires-Dist: rich>=13.9.4
Requires-Dist: tiktoken>=0.8.0
Requires-Dist: textual>=0.84.0
Dynamic: author
Dynamic: license-file
Dynamic: requires-python
